[{"model": "admin.logentry", "pk": 1, "fields": {"action_time": "2025-07-14T19:13:15.514Z", "user": 1, "content_type": 9, "object_id": "4", "object_repr": "MD — OR — 12345", "action_flag": 1, "change_message": "[{\"added\": {}}]"}}, {"model": "admin.logentry", "pk": 2, "fields": {"action_time": "2025-07-14T19:17:45.679Z", "user": 1, "content_type": 9, "object_id": "4", "object_repr": "MD — OR — 12345", "action_flag": 2, "change_message": "[{\"changed\": {\"fields\": [\"Expiration date\"]}}]"}}, {"model": "admin.logentry", "pk": 3, "fields": {"action_time": "2025-07-14T19:17:50.118Z", "user": 1, "content_type": 9, "object_id": "4", "object_repr": "MD — OR — 12345", "action_flag": 2, "change_message": "[]"}}, {"model": "auth.user", "pk": 1, "fields": {"password": "pbkdf2_sha256$1000000$F2wiWe1lZHXy4z3eKYNfRV$z84h5sSElN1cJlsPT2Uc9zVSi+gVynskNxJeGRfffMA=", "last_login": "2025-07-14T17:52:11.117Z", "is_superuser": true, "username": "jakestone", "first_name": "", "last_name": "", "email": "jakelawrencestone@gmail.com", "is_staff": true, "is_active": true, "date_joined": "2025-07-14T17:51:55.178Z", "groups": [], "user_permissions": []}}, {"model": "sessions.session", "pk": "m0j94e34r4s8eycu1om0pkg2eoowpy3j", "fields": {"session_data": ".eJxVjEEOwiAQRe_C2hAGChSX7j0DGWBGqoYmpV0Z765NutDtf-_9l4i4rTVunZY4FXEWIE6_W8L8oLaDcsd2m2We27pMSe6KPGiX17nQ83K4fwcVe_3WxMGARuWzdWxS5tGp7AFQIZPSwTI5MIPz5O0QCnrO3owEpqDSDqx4fwDlLzef:1ubNLX:gDzsXdlhZ3f27TDT52UyLgtpENqHA9-TvjGC-xLKWTA", "expire_date": "2025-07-28T17:52:11.118Z"}}, {"model": "tracker.cmerule", "pk": 1, "fields": {"state": "AL", "profession": "MD", "hours_required": 50, "renewal_period": 2, "special_category": "controlled", "special_hours_required": 2.0, "notes": "2 hrs controlled substances"}}, {"model": "tracker.cmerule", "pk": 2, "fields": {"state": "AK", "profession": "MD", "hours_required": 50, "renewal_period": 2, "special_category": "opioid", "special_hours_required": 2.0, "notes": "2 hrs pain/opioid"}}, {"model": "tracker.cmerule", "pk": 3, "fields": {"state": "AZ", "profession": "MD", "hours_required": 40, "renewal_period": 2, "special_category": "opioid", "special_hours_required": 3.0, "notes": "3 hrs opioid-related CME"}}, {"model": "tracker.cmerule", "pk": 4, "fields": {"state": "AR", "profession": "MD", "hours_required": 20, "renewal_period": 1, "special_category": "opioid", "special_hours_required": 1.0, "notes": "1 hr opioids; 3 hrs first 2 yrs"}}, {"model": "tracker.cmerule", "pk": 5, "fields": {"state": "CA", "profession": "MD", "hours_required": 50, "renewal_period": 2, "special_category": "pain", "special_hours_required": 12.0, "notes": "12 hrs pain/terminal care"}}, {"model": "tracker.cmerule", "pk": 6, "fields": {"state": "CO", "profession": "MD", "hours_required": 30, "renewal_period": 2, "special_category": "opioid", "special_hours_required": 2.0, "notes": "2 hrs opioid prescribing"}}, {"model": "tracker.cmerule", "pk": 7, "fields": {"state": "CT", "profession": "MD", "hours_required": 50, "renewal_period": 2, "special_category": "controlled", "special_hours_required": 0.0, "notes": "Controlled substances"}}, {"model": "tracker.cmerule", "pk": 8, "fields": {"state": "DE", "profession": "MD", "hours_required": 40, "renewal_period": 2, "special_category": "controlled", "special_hours_required": 2.0, "notes": "2 hrs controlled substances"}}, {"model": "tracker.cmerule", "pk": 9, "fields": {"state": "DC", "profession": "MD", "hours_required": 50, "renewal_period": 2, "special_category": "public_health", "special_hours_required": 0.0, "notes": "10% public health"}}, {"model": "tracker.cmerule", "pk": 10, "fields": {"state": "FL", "profession": "MD", "hours_required": 40, "renewal_period": 2, "special_category": "opioid", "special_hours_required": 2.0, "notes": "2 hrs medical errors; 2 hrs opioids"}}, {"model": "tracker.cmerule", "pk": 11, "fields": {"state": "GA", "profession": "MD", "hours_required": 40, "renewal_period": 2, "special_category": "opioid", "special_hours_required": 3.0, "notes": "3 hrs opioid CME"}}, {"model": "tracker.cmerule", "pk": 12, "fields": {"state": "HI", "profession": "MD", "hours_required": 40, "renewal_period": 2, "special_category": "general", "special_hours_required": 0.0, "notes": "Cat 1 only"}}, {"model": "tracker.cmerule", "pk": 13, "fields": {"state": "ID", "profession": "MD", "hours_required": 40, "renewal_period": 2, "special_category": "pain", "special_hours_required": 0.0, "notes": "Pain/opioids"}}, {"model": "tracker.cmerule", "pk": 14, "fields": {"state": "IL", "profession": "MD", "hours_required": 150, "renewal_period": 3, "special_category": "bias", "special_hours_required": 60.0, "notes": "60 hrs Cat 1; 1 hr harassment/bias"}}, {"model": "tracker.cmerule", "pk": 15, "fields": {"state": "IA", "profession": "MD", "hours_required": 40, "renewal_period": 2, "special_category": "opioid", "special_hours_required": 0.0, "notes": "Abuse, opioid, dementia topics"}}, {"model": "tracker.cmerule", "pk": 16, "fields": {"state": "KS", "profession": "MD", "hours_required": 50, "renewal_period": 1, "special_category": "pain", "special_hours_required": 0.0, "notes": "Pain/practice topics"}}, {"model": "tracker.cmerule", "pk": 17, "fields": {"state": "KY", "profession": "MD", "hours_required": 60, "renewal_period": 3, "special_category": "controlled", "special_hours_required": 30.0, "notes": "30 hrs Cat 1; drug diversion"}}, {"model": "tracker.cmerule", "pk": 18, "fields": {"state": "LA", "profession": "MD", "hours_required": 20, "renewal_period": 1, "special_category": "controlled", "special_hours_required": 3.0, "notes": "3 hrs drug diversion"}}, {"model": "tracker.cmerule", "pk": 19, "fields": {"state": "ME", "profession": "MD", "hours_required": 40, "renewal_period": 2, "special_category": "opioid", "special_hours_required": 3.0, "notes": "3 hrs opioid"}}, {"model": "tracker.cmerule", "pk": 20, "fields": {"state": "MD", "profession": "MD", "hours_required": 50, "renewal_period": 2, "special_category": "opioid", "special_hours_required": 2.0, "notes": "2 hrs opioid/bias"}}, {"model": "tracker.cmerule", "pk": 21, "fields": {"state": "MA", "profession": "MD", "hours_required": 50, "renewal_period": 2, "special_category": "opioid", "special_hours_required": 0.0, "notes": "Opioid, EHR, bias, risk mgmt"}}, {"model": "tracker.cmerule", "pk": 22, "fields": {"state": "MI", "profession": "MD", "hours_required": 150, "renewal_period": 3, "special_category": "pain", "special_hours_required": 3.0, "notes": "3 hrs pain & ethics"}}, {"model": "tracker.cmerule", "pk": 23, "fields": {"state": "MN", "profession": "MD", "hours_required": 75, "renewal_period": 3, "special_category": "general", "special_hours_required": 0.0, "notes": "Cat 1 only"}}, {"model": "tracker.cmerule", "pk": 24, "fields": {"state": "MS", "profession": "MD", "hours_required": 40, "renewal_period": 2, "special_category": "controlled", "special_hours_required": 5.0, "notes": "5 hrs controlled substances"}}, {"model": "tracker.cmerule", "pk": 25, "fields": {"state": "MO", "profession": "MD", "hours_required": 50, "renewal_period": 2, "special_category": "general", "special_hours_required": 0.0, "notes": "Cat 1 only"}}, {"model": "tracker.cmerule", "pk": 26, "fields": {"state": "MT", "profession": "MD", "hours_required": 60, "renewal_period": 3, "special_category": "general", "special_hours_required": 0.0, "notes": "No specific requirements"}}, {"model": "tracker.cmerule", "pk": 27, "fields": {"state": "NE", "profession": "MD", "hours_required": 50, "renewal_period": 2, "special_category": "general", "special_hours_required": 0.0, "notes": "No specific requirements"}}, {"model": "tracker.cmerule", "pk": 28, "fields": {"state": "NV", "profession": "MD", "hours_required": 40, "renewal_period": 2, "special_category": "suicide", "special_hours_required": 2.0, "notes": "2 hrs suicide; 4 hrs controlled substances"}}, {"model": "tracker.cmerule", "pk": 29, "fields": {"state": "NH", "profession": "MD", "hours_required": 100, "renewal_period": 2, "special_category": "opioid", "special_hours_required": 3.0, "notes": "3 hrs opioids"}}, {"model": "tracker.cmerule", "pk": 30, "fields": {"state": "NJ", "profession": "MD", "hours_required": 100, "renewal_period": 2, "special_category": "opioid", "special_hours_required": 0.0, "notes": "Opioid topics required"}}, {"model": "tracker.cmerule", "pk": 31, "fields": {"state": "NM", "profession": "MD", "hours_required": 75, "renewal_period": 3, "special_category": "pain", "special_hours_required": 5.0, "notes": "5 hrs pain management Yr 1"}}, {"model": "tracker.cmerule", "pk": 32, "fields": {"state": "NY", "profession": "MD", "hours_required": 0, "renewal_period": 2, "special_category": "child_abuse", "special_hours_required": 3.0, "notes": "Child abuse, infections, 3 hrs pain if DEA"}}, {"model": "tracker.cmerule", "pk": 33, "fields": {"state": "NC", "profession": "MD", "hours_required": 60, "renewal_period": 3, "special_category": "controlled", "special_hours_required": 3.0, "notes": "3 hrs controlled substances"}}, {"model": "tracker.cmerule", "pk": 34, "fields": {"state": "ND", "profession": "MD", "hours_required": 40, "renewal_period": 2, "special_category": "general", "special_hours_required": 0.0, "notes": "Cat 1 only"}}, {"model": "tracker.cmerule", "pk": 35, "fields": {"state": "OH", "profession": "MD", "hours_required": 50, "renewal_period": 2, "special_category": "ethics", "special_hours_required": 1.0, "notes": "1 hr reporting duty"}}, {"model": "tracker.cmerule", "pk": 36, "fields": {"state": "OK", "profession": "MD", "hours_required": 60, "renewal_period": 3, "special_category": "pain", "special_hours_required": 1.0, "notes": "1 hr pain annually"}}, {"model": "tracker.cmerule", "pk": 37, "fields": {"state": "OR", "profession": "MD", "hours_required": 60, "renewal_period": 2, "special_category": "pain", "special_hours_required": 6.0, "notes": "6 hrs pain management"}}, {"model": "tracker.cmerule", "pk": 38, "fields": {"state": "PA", "profession": "MD", "hours_required": 100, "renewal_period": 2, "special_category": "opioid", "special_hours_required": 2.0, "notes": "2 hrs opioids; 2 hrs child abuse"}}, {"model": "tracker.cmerule", "pk": 39, "fields": {"state": "RI", "profession": "MD", "hours_required": 40, "renewal_period": 2, "special_category": "opioid", "special_hours_required": 0.0, "notes": "Opioids and risk topics"}}, {"model": "tracker.cmerule", "pk": 40, "fields": {"state": "SC", "profession": "MD", "hours_required": 40, "renewal_period": 2, "special_category": "ethics", "special_hours_required": 0.0, "notes": "Opioid and ethics"}}, {"model": "tracker.cmerule", "pk": 41, "fields": {"state": "SD", "profession": "MD", "hours_required": 0, "renewal_period": 2, "special_category": "general", "special_hours_required": 0.0, "notes": "No CME required"}}, {"model": "tracker.cmerule", "pk": 42, "fields": {"state": "TN", "profession": "MD", "hours_required": 40, "renewal_period": 2, "special_category": "opioid", "special_hours_required": 0.0, "notes": "Opioids & prescribing practices"}}, {"model": "tracker.cmerule", "pk": 43, "fields": {"state": "TX", "profession": "MD", "hours_required": 48, "renewal_period": 2, "special_category": "ethics", "special_hours_required": 2.0, "notes": "2 hrs ethics + pain/human trafficking"}}, {"model": "tracker.cmerule", "pk": 44, "fields": {"state": "UT", "profession": "MD", "hours_required": 40, "renewal_period": 2, "special_category": "controlled", "special_hours_required": 3.5, "notes": "3.5 hrs controlled + suicide"}}, {"model": "tracker.cmerule", "pk": 45, "fields": {"state": "VT", "profession": "MD", "hours_required": 30, "renewal_period": 2, "special_category": "controlled", "special_hours_required": 1.0, "notes": "1 hr palliative; controlled subs"}}, {"model": "tracker.cmerule", "pk": 46, "fields": {"state": "VA", "profession": "MD", "hours_required": 60, "renewal_period": 2, "special_category": "general", "special_hours_required": 30.0, "notes": "30 hrs Cat 1"}}, {"model": "tracker.cmerule", "pk": 47, "fields": {"state": "WA", "profession": "MD", "hours_required": 200, "renewal_period": 4, "special_category": "suicide", "special_hours_required": 6.0, "notes": "6 hrs suicide; 2 hrs equity"}}, {"model": "tracker.cmerule", "pk": 48, "fields": {"state": "WV", "profession": "MD", "hours_required": 50, "renewal_period": 2, "special_category": "controlled", "special_hours_required": 3.0, "notes": "3 hrs controlled substances"}}, {"model": "tracker.cmerule", "pk": 49, "fields": {"state": "WI", "profession": "MD", "hours_required": 30, "renewal_period": 2, "special_category": "opioid", "special_hours_required": 2.0, "notes": "2 hrs opioid"}}, {"model": "tracker.cmerule", "pk": 50, "fields": {"state": "WY", "profession": "MD", "hours_required": 60, "renewal_period": 3, "special_category": "controlled", "special_hours_required": 0.0, "notes": "Controlled substances"}}, {"model": "tracker.cmerule", "pk": 51, "fields": {"state": "ZZ", "profession": "MD", "hours_required": 50, "renewal_period": 3, "special_category": "opioid", "special_hours_required": 12.0, "notes": "User-defined custom rule"}}, {"model": "tracker.cmerule", "pk": 52, "fields": {"state": "ZZ", "profession": "MD", "hours_required": 60, "renewal_period": 3, "special_category": "opioid", "special_hours_required": 12.0, "notes": "User-defined custom rule"}}, {"model": "tracker.medicallicense", "pk": 4, "fields": {"user": 1, "profession": "MD", "state": "OR", "license_number": "12345", "status": "Active", "issue_date": "2023-12-20", "expiration_date": "2025-07-29", "rule": 1}}, {"model": "tracker.reminderlog", "pk": 1, "fields": {"user": 1, "license": 4, "days_before": 1, "sent_at": "2025-07-14T19:13:34.388Z"}}, {"model": "tracker.reminderlog", "pk": 2, "fields": {"user": 1, "license": 4, "days_before": 15, "sent_at": "2025-07-14T19:27:20.332Z"}}]